[
  {"username":"panda","password":"ryanthepandalovesbamboo","god":"Itzamma","admin":true},
  
  
  {"username":"bluewhale","password":"stormeyes","god":"Chac","favorite color":"blue",admin":true}
  ,{"username":"kiwi" ,"password":"tyler","god":"Huracan","admin":false}
,{"username":"mas","password":"alla", "god":"none","admin":false}
,{"username":"pandabamboo","password":"pandalovesbamboo","god":"Ah-Tabai","admin":false}
,{"username":"whitetiger","password":"naturequeen","god":"Ah-Wink-Ir-Masa","admin":false}
,{"username":"deathrunner","password":"dewey","god":"Ahulane","admin":false}
,{"username":"pusheen","password":"pusheen","god":"Alaghom-Naom-Tzentel","admin":false}
,{"username":"unicorn","password":"creationmaster","god":"Alom","admin":false}
,{"username":"puppy","password":"puppiesrule","god":"Colop-U-Uichikin","admin":false}
,{"username":"henry","password":"dogs","god":"Kinich Ahau","admin":false}
,{"username":"hermione ","password":"Hermione","god":"Ahau-Chamahez","admin":false}



]
